LICENSE.md
README.md
pyproject.toml
setup.cfg
setup.py
src/data_file_merge.egg-info/PKG-INFO
src/data_file_merge.egg-info/SOURCES.txt
src/data_file_merge.egg-info/dependency_links.txt
src/data_file_merge.egg-info/top_level.txt
src/dfm/__init__.py
src/dfm/cli.py
src/dfm/config.py
src/dfm/exceptions.py
src/dfm/file_location.py
src/dfm/file_types.py
src/dfm/json_merger.py
src/dfm/naming_conventions.py
src/dfm/reference_types.py
src/dfm/regex.py
src/dfm/version.py