Metadata-Version: 2.1
Name: data-file-merge
Version: 0.3.1
Summary: Config-driven merging and splitting of JSON data files.
Home-page: https://github.com/ServerlessSam/data-file-merge
Author: Samuel Lock
Author-email: serverlesssam@gmail.com
License: MIT
Keywords: configuration management merge split yaml json data files
License-File: LICENSE.md
